IUNI/IUNI.py
IUNI/__init__.py
IUNI-0.0.2.dist-info/METADATA
IUNI-0.0.2.dist-info/WHEEL
IUNI-0.0.2.dist-info/top_level.txt
IUNI-0.0.2.dist-info/RECORD
