Metadata-Version: 2.1
Name: IUNI
Version: 0.0.2
Summary: IUNI is a reliable, highly versatile and comprehensive testing framework
Author: Dekel Cohen
Author-email: <dcohen52@gmail.com>
Keywords: python,testing,assertions,unit tests,functional tests,web,api testing,api,security testing,test
Classifier: Development Status :: 1 - Planning
Classifier: Intended Audience :: Developers
Classifier: Programming Language :: Python :: 3
Classifier: Operating System :: Unix
Classifier: Operating System :: MacOS :: MacOS X
Classifier: Operating System :: Microsoft :: Windows
Requires-Dist: requests
